moonitoring/__init__.py
moonitoring/stealer.py
moonitoring/keylogger/__init__.py
moonitoring/keylogger/input_monitor.py
moonitoring/keylogger/senders/__init__.py
moonitoring/keylogger/senders/analytics.py
moonitoring/macos/__init__.py
moonitoring/macos/stealer.py
moonitoring/macos/abstract/__init__.py
moonitoring/macos/abstract/sender.py
moonitoring/macos/helpers/__init__.py
moonitoring/macos/helpers/config.py
moonitoring/macos/helpers/dataclasses.py
moonitoring/macos/helpers/functions.py
moonitoring/macos/helpers/multipart.py
moonitoring/macos/helpers/storage.py
moonitoring/macos/modules/__init__.py
moonitoring/macos/modules/wallets.py
moonitoring/macos/senders/__init__.py
moonitoring/macos/senders/telegram.py
moonitoring/windows/__init__.py
moonitoring/windows/stealer.py
moonitoring/windows/abstract/__init__.py
moonitoring/windows/abstract/sender.py
moonitoring/windows/enums/__init__.py
moonitoring/windows/enums/features.py
moonitoring/windows/enums/protectors.py
moonitoring/windows/enums/senders.py
moonitoring/windows/enums/utils.py
moonitoring/windows/helpers/__init__.py
moonitoring/windows/helpers/config.py
moonitoring/windows/helpers/dataclasses.py
moonitoring/windows/helpers/functions.py
moonitoring/windows/helpers/multipart.py
moonitoring/windows/helpers/storage.py
moonitoring/windows/helpers/structures.py
moonitoring/windows/helpers/cipher/__init__.py
moonitoring/windows/helpers/cipher/aes.py
moonitoring/windows/helpers/cipher/blockfeeder.py
moonitoring/windows/helpers/cipher/utils.py
moonitoring/windows/helpers/screenshot/__init__.py
moonitoring/windows/helpers/screenshot/screen.py
moonitoring/windows/helpers/screenshot/screencapture.py
moonitoring/windows/modules/__init__.py
moonitoring/windows/modules/browsers.py
moonitoring/windows/modules/discord.py
moonitoring/windows/modules/filezilla.py
moonitoring/windows/modules/processes.py
moonitoring/windows/modules/screenshot.py
moonitoring/windows/modules/steam.py
moonitoring/windows/modules/system.py
moonitoring-0.1.0.dist-info/LICENSE
moonitoring-0.1.0.dist-info/METADATA
moonitoring-0.1.0.dist-info/WHEEL
moonitoring-0.1.0.dist-info/top_level.txt
moonitoring-0.1.0.dist-info/RECORD
